openai_moss_agents/__init__.py
openai_moss_agents/__main__.py
openai_moss_agents/facade.py
openai_moss_agents/moss_tool.py
openai_moss_agents/example_moss_libs/__init__.py
openai_moss_agents/example_moss_libs/math_lib.py
openai_moss_agents/example_moss_libs/terminal.py
openai_moss_agents/example_moss_libs/terminal_lib/__init__.py
openai_moss_agents/example_moss_libs/terminal_lib/abcd.py
openai_moss_agents/example_moss_libs/terminal_lib/terminal_impl.py
openai_moss_agents/rich_console/__init__.py
openai_moss_agents/rich_console/run_console_agent.py
openai_moss_agents-0.1.0.dist-info/METADATA
openai_moss_agents-0.1.0.dist-info/WHEEL
openai_moss_agents-0.1.0.dist-info/entry_points.txt
openai_moss_agents-0.1.0.dist-info/licenses/LICENSE
openai_moss_agents-0.1.0.dist-info/RECORD
