Metadata-Version: 2.4
Name: openai-moss-agents
Version: 0.1.0
Summary: make python module as code interpreter tool for OpenAI Agent by MOSS protocol
Author-email: thirdgerb <thirdgerb@gmail.com>
License-File: LICENSE
Requires-Python: >=3.10
Requires-Dist: ghostos-moss>=0.3.7
Requires-Dist: openai-agents>=0.0.3
